lwcharts/__init__.py
lwcharts/chart.py
lwcharts-0.1.1.dist-info/licenses/LICENSE
lwcharts-0.1.1.dist-info/METADATA
lwcharts-0.1.1.dist-info/WHEEL
lwcharts-0.1.1.dist-info/top_level.txt
lwcharts-0.1.1.dist-info/RECORD
