Metadata-Version: 2.4
Name: lwcharts
Version: 0.1.1
Summary: TradingView Lightweight Charts for Jupyter notebooks
Author: lwcharts contributors
License: Apache-2.0
Project-URL: Homepage, https://github.com/deepentropy/lwcharts
Project-URL: Documentation, https://github.com/deepentropy/lwcharts#readme
Project-URL: Repository, https://github.com/deepentropy/lwcharts
Project-URL: Bug Tracker, https://github.com/deepentropy/lwcharts/issues
Keywords: jupyter,charts,tradingview,lightweight-charts,visualization,trading,finance
Classifier: Development Status :: 3 - Alpha
Classifier: Framework :: Jupyter
Classifier: Framework :: Jupyter :: JupyterLab
Classifier: Intended Audience :: Developers
Classifier: Intended Audience :: Science/Research
Classifier: Intended Audience :: Financial and Insurance Industry
Classifier: License :: OSI Approved :: Apache Software License
Classifier: Programming Language :: Python
Classifier: Programming Language :: Python :: 3.9
Classifier: Programming Language :: Python :: 3.10
Classifier: Programming Language :: Python :: 3.11
Classifier: Programming Language :: Python :: 3.12
Classifier: Topic :: Scientific/Engineering :: Visualization
Requires-Python: >=3.7
License-File: LICENSE
Requires-Dist: ipython>=7.0.0
Provides-Extra: dev
Requires-Dist: pytest>=7.0; extra == "dev"
Requires-Dist: black>=22.0; extra == "dev"
Requires-Dist: build>=0.10.0; extra == "dev"
Dynamic: license-file
